odoo/addons/repair_order_group_services/README.rst
odoo/addons/repair_order_group_services/__init__.py
odoo/addons/repair_order_group_services/__manifest__.py
odoo/addons/repair_order_group_services/i18n/repair_order_group_services.pot
odoo/addons/repair_order_group_services/models/__init__.py
odoo/addons/repair_order_group_services/models/repair_order.py
odoo/addons/repair_order_group_services/models/repair_service.py
odoo/addons/repair_order_group_services/readme/CONTRIBUTORS.md
odoo/addons/repair_order_group_services/readme/DESCRIPTION.md
odoo/addons/repair_order_group_services/readme/USAGE.md
odoo/addons/repair_order_group_services/readme/newsfragments/.gitkeep
odoo/addons/repair_order_group_services/static/description/icon.png
odoo/addons/repair_order_group_services/static/description/icon.svg
odoo/addons/repair_order_group_services/static/description/index.html
odoo/addons/repair_order_group_services/tests/__init__.py
odoo/addons/repair_order_group_services/tests/test_repair_order_group_service.py
odoo_addon_repair_order_group_services-18.0.1.0.0.2.dist-info/METADATA
odoo_addon_repair_order_group_services-18.0.1.0.0.2.dist-info/WHEEL
odoo_addon_repair_order_group_services-18.0.1.0.0.2.dist-info/top_level.txt
odoo_addon_repair_order_group_services-18.0.1.0.0.2.dist-info/RECORD
